dj_queue_health/__init__.py
dj_queue_health/apps.py
dj_queue_health/management/__init__.py
dj_queue_health/management/commands/__init__.py
dj_queue_health/management/commands/test_queue_health.py
dj_queue_health/management/commands/update_queue_timestamp.py
dj_queue_health-1.0.0.dist-info/WHEEL
dj_queue_health-1.0.0.dist-info/METADATA
dj_queue_health-1.0.0.dist-info/RECORD
