Metadata-Version: 2.1
Name: dj_queue_health
Version: 1.0.0
Summary: django app for checking queue health. Targeted to be used for Kubernetes deployments
Home-page: https://github.com/yezz123/dj-queue-health
Author: Yasser Tahiri
Author-email: yasserth19@gmail.com
Requires-Python: >=3.8
Classifier: License :: OSI Approved :: MIT License
Classifier: Operating System :: OS Independent
Classifier: Intended Audience :: Developers
Classifier: Intended Audience :: Information Technology
Classifier: Natural Language :: English
Classifier: Framework :: Django
Classifier: Programming Language :: Python
Classifier: Programming Language :: Python :: 3.8
Classifier: Programming Language :: Python :: 3.9
Classifier: Programming Language :: Python :: 3.10
Classifier: Programming Language :: Python :: 3 :: Only
Classifier: Topic :: Internet :: WWW/HTTP :: Session
Classifier: Topic :: Internet :: WWW/HTTP :: HTTP Servers
Classifier: Topic :: Utilities
Classifier: Typing :: Typed
Requires-Dist: Django
Requires-Dist: django_rq
Requires-Dist: celery
Requires-Dist: pre-commit==2.19.0 ; extra == "dev"
Requires-Dist: pytest ; extra == "dev"
Requires-Dist: pytest-django ; extra == "dev"
Provides-Extra: dev
